mlflow_ibmcos/__init__.py
mlflow_ibmcos/logger.py
mlflow_ibmcos/model_registry.py
mlflow_ibmcos/py.typed
mlflow_ibmcos/schemas.py
mlflow_ibmcos/utils.py
mlflow_ibmcos/core/__init__.py
mlflow_ibmcos/core/decorators.py
mlflow_ibmcos/core/exceptions.py
mlflow_ibmcos-0.1.9.dist-info/METADATA
mlflow_ibmcos-0.1.9.dist-info/WHEEL
mlflow_ibmcos-0.1.9.dist-info/RECORD
